bezier_interpolation/__init__.py
bezier_interpolation/cubic_interpolation.py
bezier_interpolation/quadratic_interpolation.py
bezier_interpolation-0.0.2.dist-info/METADATA
bezier_interpolation-0.0.2.dist-info/WHEEL
bezier_interpolation-0.0.2.dist-info/top_level.txt
bezier_interpolation-0.0.2.dist-info/RECORD
